LICENSE
MANIFEST.in
METHOD.txt
README.rst
lua_call.py
setup.py
lua_call.egg-info/PKG-INFO
lua_call.egg-info/SOURCES.txt
lua_call.egg-info/dependency_links.txt
lua_call.egg-info/top_level.txt