Metadata-Version: 1.0
Name: lua-call
Version: 0.10.0
Summary: Call Lua scripts from other Lua scripts in Redis
Home-page: http://github.com/josiahcarlson/lua-call/
Author: Josiah Carlson
Author-email: josiah.carlson@gmail.com
License: MIT
Download-URL: http://pypi.python.org/pypi/lua_call/
Platform: UNKNOWN
Classifier: Programming Language :: Python :: 2
Classifier: Programming Language :: Python :: 2.6
Classifier: Programming Language :: Python :: 2.7
Classifier: Intended Audience :: Developers
Classifier: License :: OSI Approved :: MIT License
Classifier: Topic :: Software Development :: Libraries
Classifier: Topic :: Utilities
